CHANGELOG.md
LICENSE
py.typed
cy_serial_bridge/__init__.py
cy_serial_bridge/cli.py
cy_serial_bridge/configuration_block.py
cy_serial_bridge/cy_scb_context.py
cy_serial_bridge/driver.py
cy_serial_bridge/py.typed
cy_serial_bridge/usb_constants.py
cy_serial_bridge/utils.py
cy_serial_bridge-0.3.2.dist-info/LICENSE
cy_serial_bridge-0.3.2.dist-info/METADATA
cy_serial_bridge-0.3.2.dist-info/WHEEL
cy_serial_bridge-0.3.2.dist-info/entry_points.txt
cy_serial_bridge-0.3.2.dist-info/RECORD
