Metadata-Version: 2.1
Name: cy_serial_bridge
Version: 0.3.2
Summary: Pure Python driver for using and reconfiguring the CY7C652xx family of USB to SPI/I2C/UART bridge ICs.
Home-page: https://github.com/mbed-ce/cy_serial_bridge/
Author: Jamie Smith
Author-email: smit109@usc.edu
Requires-Python: >=3.10,<4.0
Classifier: Programming Language :: Python :: 3
Classifier: Programming Language :: Python :: 3.10
Classifier: Programming Language :: Python :: 3.11
Classifier: Programming Language :: Python :: 3.12
Requires-Dist: click (>=8.0,<9.0)
Requires-Dist: libusb1 (>=3.0.0,<4.0.0)
Requires-Dist: pyserial (>=3.5,<4.0)
Requires-Dist: rich (>=13.6,<14.0)
Requires-Dist: typer (>=0.9,<0.10)
Project-URL: Repository, https://github.com/mbed-ce/cy_serial_bridge/
Project-URL: Tracker, https://github.com/mbed-ce/cy_serial_bridge/issues
